simple_package_ssakg/__init__.py
simple_package_ssakg/module1.py
simple_package_ssakg/module2.py
simple_package_ssakg/utils/__init__.py
simple_package_ssakg/utils/generator.py
simple_package_ssakg-0.0.2.dist-info/LICENSE
simple_package_ssakg-0.0.2.dist-info/METADATA
simple_package_ssakg-0.0.2.dist-info/WHEEL
simple_package_ssakg-0.0.2.dist-info/top_level.txt
simple_package_ssakg-0.0.2.dist-info/RECORD
