Metadata-Version: 2.1
Name: simple_package_ssakg
Version: 0.0.2
Summary: My first Python package
Home-page: 
Author: Przemysław Stokłosa
Author-email: przemyslaw.stoklosa@gmail.com
Keywords: python,first package
Classifier: Development Status :: 1 - Planning
Classifier: Intended Audience :: Education
Classifier: Programming Language :: Python :: 3
Classifier: License :: OSI Approved :: MIT License
Classifier: Operating System :: OS Independent
Requires-Python: >=3.11
License-File: LICENSE
Requires-Dist: numpy~=2.1.2
